namevariable/__init__.py
namevariable/frequency.py
namevariable/gender.py
dedupe_variable_name-1.0.0.dist-info/METADATA
dedupe_variable_name-1.0.0.dist-info/WHEEL
dedupe_variable_name-1.0.0.dist-info/top_level.txt
dedupe_variable_name-1.0.0.dist-info/RECORD
