Metadata-Version: 2.1
Name: dedupe-variable-name
Version: 1.0.0
Summary: Name variable type for dedupe
Home-page: https://github.com/datamade/dedupe-variables-name
License: The MIT License: http://www.opensource.org/licenses/mit-license.php
Requires-Dist: probablepeople >=0.5
Requires-Dist: parseratorvariable >=1.0.0
